{
  "appInfo" : {
    "build" : "252.25436",
    "buildDate" : "2025-09-20T05:30:59.434Z[Etc/UTC]",
    "productCode" : "QDJVMC",
    "generated" : "2025-09-20T05:31:06.52488796Z",
    "os" : "Linux 6.11.0-1018-azure",
    "runtime" : "JetBrains s.r.o. 21.0.8 21.0.8+9-b1038.68"
  },
  "runtimeInfo" : {
    "maxMemory" : 11744051200,
    "numberOfProcessors" : 4,
    "maxNumberOfIndexingThreads" : 4,
    "maxSizeOfFileForIntelliSense" : 2560000,
    "maxSizeOfFileForContentLoading" : 20971520
  },
  "type" : "DumbIndexing",
  "projectIndexingActivityHistory" : {
    "projectName" : "project",
    "times" : {
      "scanningIds" : [ 0 ],
      "contentLoadingVisibleTime" : 78067720,
      "retrievingChangedDuringIndexingFilesTime" : 3142539,
      "separateApplyingIndexesVisibleTime" : 112870075,
      "updatingStart" : "2025-09-20T05:31:05.293107665Z",
      "updatingEnd" : "2025-09-20T05:31:06.522534032Z",
      "totalWallTimeWithPauses" : 1229426367,
      "wallTimeOnPause" : 0,
      "isCancelled" : false,
      "dumbWallTimeWithPauses" : 1229426367,
      "dumbWallTimeWithoutPauses" : 1229426367,
      "dumbModeStart" : "2025-09-20T05:31:05.293107665Z",
      "totalWallTimeWithoutPauses" : 1229426367
    },
    "fileCount" : {
      "numberOfChangedDuringIndexingFiles" : 33,
      "numberOfFilesIndexedByInfrastructureExtensionsDuringIndexingStage" : 0,
      "numberOfFilesIndexedWithLoadingContent" : 43,
      "numberOfNothingToWriteFiles" : 0
    },
    "totalStatsPerFileType" : [ {
      "fileType" : "XML",
      "partOfTotalProcessingTime" : {
        "part" : 2019477652,
        "total" : 3261812049
      },
      "partOfTotalContentLoadingTime" : {
        "part" : 85276743,
        "total" : 184848077
      },
      "totalNumberOfFiles" : 4,
      "totalFilesSize" : 4975532,
      "totalProcessingSpeed" : {
        "totalBytes" : 4975532,
        "totalCpuTime" : 2019477652
      },
      "biggestContributors" : [ {
        "providerName" : "Refreshed files",
        "numberOfFiles" : 4,
        "totalFilesSize" : 4975532,
        "partOfTotalProcessingTimeOfThisFileType" : {
          "part" : 2019477652,
          "total" : 2019477652
        }
      } ]
    }, {
      "fileType" : "HTML",
      "partOfTotalProcessingTime" : {
        "part" : 610200222,
        "total" : 3261812049
      },
      "partOfTotalContentLoadingTime" : {
        "part" : 60635918,
        "total" : 184848077
      },
      "totalNumberOfFiles" : 6,
      "totalFilesSize" : 158829,
      "totalProcessingSpeed" : {
        "totalBytes" : 158829,
        "totalCpuTime" : 610200222
      },
      "biggestContributors" : [ {
        "providerName" : "Refreshed files",
        "numberOfFiles" : 5,
        "totalFilesSize" : 111174,
        "partOfTotalProcessingTimeOfThisFileType" : {
          "part" : 412523965,
          "total" : 610200222
        }
      }, {
        "providerName" : "<indexing queue>",
        "numberOfFiles" : 1,
        "totalFilesSize" : 47655,
        "partOfTotalProcessingTimeOfThisFileType" : {
          "part" : 197676257,
          "total" : 610200222
        }
      } ]
    }, {
      "fileType" : "PLAIN_TEXT",
      "partOfTotalProcessingTime" : {
        "part" : 389257945,
        "total" : 3261812049
      },
      "partOfTotalContentLoadingTime" : {
        "part" : 23342639,
        "total" : 184848077
      },
      "totalNumberOfFiles" : 10,
      "totalFilesSize" : 886305,
      "totalProcessingSpeed" : {
        "totalBytes" : 886305,
        "totalCpuTime" : 389257945
      },
      "biggestContributors" : [ {
        "providerName" : "<indexing queue>",
        "numberOfFiles" : 5,
        "totalFilesSize" : 162287,
        "partOfTotalProcessingTimeOfThisFileType" : {
          "part" : 211301882,
          "total" : 389257945
        }
      }, {
        "providerName" : "Refreshed files",
        "numberOfFiles" : 5,
        "totalFilesSize" : 724018,
        "partOfTotalProcessingTimeOfThisFileType" : {
          "part" : 177956063,
          "total" : 389257945
        }
      } ]
    }, {
      "fileType" : "JSON",
      "partOfTotalProcessingTime" : {
        "part" : 126121426,
        "total" : 3261812049
      },
      "partOfTotalContentLoadingTime" : {
        "part" : 8993675,
        "total" : 184848077
      },
      "totalNumberOfFiles" : 17,
      "totalFilesSize" : 139260,
      "totalProcessingSpeed" : {
        "totalBytes" : 139260,
        "totalCpuTime" : 126121426
      },
      "biggestContributors" : [ {
        "providerName" : "Refreshed files",
        "numberOfFiles" : 15,
        "totalFilesSize" : 138076,
        "partOfTotalProcessingTimeOfThisFileType" : {
          "part" : 117466954,
          "total" : 126121426
        }
      }, {
        "providerName" : "<indexing queue>",
        "numberOfFiles" : 2,
        "totalFilesSize" : 1184,
        "partOfTotalProcessingTimeOfThisFileType" : {
          "part" : 8654472,
          "total" : 126121426
        }
      } ]
    }, {
      "fileType" : "JAVA",
      "partOfTotalProcessingTime" : {
        "part" : 93141293,
        "total" : 3261812049
      },
      "partOfTotalContentLoadingTime" : {
        "part" : 3892680,
        "total" : 184848077
      },
      "totalNumberOfFiles" : 1,
      "totalFilesSize" : 186,
      "totalProcessingSpeed" : {
        "totalBytes" : 186,
        "totalCpuTime" : 93141293
      },
      "biggestContributors" : [ {
        "providerName" : "<indexing queue>",
        "numberOfFiles" : 1,
        "totalFilesSize" : 186,
        "partOfTotalProcessingTimeOfThisFileType" : {
          "part" : 93141293,
          "total" : 93141293
        }
      } ]
    }, {
      "fileType" : "CSV/TSV",
      "partOfTotalProcessingTime" : {
        "part" : 20353479,
        "total" : 3261812049
      },
      "partOfTotalContentLoadingTime" : {
        "part" : 2394248,
        "total" : 184848077
      },
      "totalNumberOfFiles" : 4,
      "totalFilesSize" : 18581,
      "totalProcessingSpeed" : {
        "totalBytes" : 18581,
        "totalCpuTime" : 20353479
      },
      "biggestContributors" : [ {
        "providerName" : "<indexing queue>",
        "numberOfFiles" : 1,
        "totalFilesSize" : 17955,
        "partOfTotalProcessingTimeOfThisFileType" : {
          "part" : 15756929,
          "total" : 20353479
        }
      }, {
        "providerName" : "Refreshed files",
        "numberOfFiles" : 3,
        "totalFilesSize" : 626,
        "partOfTotalProcessingTimeOfThisFileType" : {
          "part" : 4596550,
          "total" : 20353479
        }
      } ]
    }, {
      "fileType" : "SARIF",
      "partOfTotalProcessingTime" : {
        "part" : 3260032,
        "total" : 3261812049
      },
      "partOfTotalContentLoadingTime" : {
        "part" : 312174,
        "total" : 184848077
      },
      "totalNumberOfFiles" : 1,
      "totalFilesSize" : 1930,
      "totalProcessingSpeed" : {
        "totalBytes" : 1930,
        "totalCpuTime" : 3260032
      },
      "biggestContributors" : [ {
        "providerName" : "Refreshed files",
        "numberOfFiles" : 1,
        "totalFilesSize" : 1930,
        "partOfTotalProcessingTimeOfThisFileType" : {
          "part" : 3260032,
          "total" : 3260032
        }
      } ]
    } ],
    "totalStatsPerBaseLanguage" : [ {
      "language" : "XML",
      "partOfTotalProcessingTime" : {
        "part" : 2629677874,
        "total" : 3261812049
      },
      "partOfTotalContentLoadingTime" : {
        "part" : 245483995,
        "total" : 184848077
      },
      "totalNumberOfFiles" : 10,
      "totalFilesSize" : 5134361,
      "totalProcessingSpeed" : {
        "totalBytes" : 5134361,
        "totalCpuTime" : 2629677874
      }
    }, {
      "language" : "HTML",
      "partOfTotalProcessingTime" : {
        "part" : 610200222,
        "total" : 3261812049
      },
      "partOfTotalContentLoadingTime" : {
        "part" : 245483995,
        "total" : 184848077
      },
      "totalNumberOfFiles" : 6,
      "totalFilesSize" : 158829,
      "totalProcessingSpeed" : {
        "totalBytes" : 158829,
        "totalCpuTime" : 610200222
      }
    }, {
      "language" : "TEXT",
      "partOfTotalProcessingTime" : {
        "part" : 409611424,
        "total" : 3261812049
      },
      "partOfTotalContentLoadingTime" : {
        "part" : 187242325,
        "total" : 184848077
      },
      "totalNumberOfFiles" : 14,
      "totalFilesSize" : 904886,
      "totalProcessingSpeed" : {
        "totalBytes" : 904886,
        "totalCpuTime" : 409611424
      }
    }, {
      "language" : "JSON",
      "partOfTotalProcessingTime" : {
        "part" : 129381458,
        "total" : 3261812049
      },
      "partOfTotalContentLoadingTime" : {
        "part" : 193841752,
        "total" : 184848077
      },
      "totalNumberOfFiles" : 18,
      "totalFilesSize" : 141190,
      "totalProcessingSpeed" : {
        "totalBytes" : 141190,
        "totalCpuTime" : 129381458
      }
    }, {
      "language" : "JAVA",
      "partOfTotalProcessingTime" : {
        "part" : 93141293,
        "total" : 3261812049
      },
      "partOfTotalContentLoadingTime" : {
        "part" : 188740757,
        "total" : 184848077
      },
      "totalNumberOfFiles" : 1,
      "totalFilesSize" : 186,
      "totalProcessingSpeed" : {
        "totalBytes" : 186,
        "totalCpuTime" : 93141293
      }
    } ],
    "totalStatsPerIndexer" : [ {
      "indexId" : "IdIndex",
      "shardsCount" : 1,
      "partOfTotalIndexingTime" : {
        "part" : 1400544672,
        "total" : 2812799660
      },
      "totalNumberOfFiles" : 43,
      "totalNumberOfFilesIndexedByExtensions" : 0,
      "totalFilesSize" : 6180623,
      "indexValueChangerEvaluationSpeed" : {
        "totalBytes" : 6180623,
        "totalCpuTime" : 1400544672
      }
    }, {
      "indexId" : "Trigram.Index",
      "shardsCount" : 1,
      "partOfTotalIndexingTime" : {
        "part" : 835791894,
        "total" : 2812799660
      },
      "totalNumberOfFiles" : 43,
      "totalNumberOfFilesIndexedByExtensions" : 0,
      "totalFilesSize" : 6180623,
      "indexValueChangerEvaluationSpeed" : {
        "totalBytes" : 6180623,
        "totalCpuTime" : 835791894
      }
    }, {
      "indexId" : "Stubs",
      "shardsCount" : 1,
      "partOfTotalIndexingTime" : {
        "part" : 325636901,
        "total" : 2812799660
      },
      "totalNumberOfFiles" : 10,
      "totalNumberOfFilesIndexedByExtensions" : 0,
      "totalFilesSize" : 5134361,
      "indexValueChangerEvaluationSpeed" : {
        "totalBytes" : 5134361,
        "totalCpuTime" : 325636901
      }
    }, {
      "indexId" : "DomFileIndex",
      "shardsCount" : 1,
      "partOfTotalIndexingTime" : {
        "part" : 82424752,
        "total" : 2812799660
      },
      "totalNumberOfFiles" : 4,
      "totalNumberOfFilesIndexedByExtensions" : 0,
      "totalFilesSize" : 4975532,
      "indexValueChangerEvaluationSpeed" : {
        "totalBytes" : 4975532,
        "totalCpuTime" : 82424752
      }
    }, {
      "indexId" : "html5.custom.attributes.index",
      "shardsCount" : 1,
      "partOfTotalIndexingTime" : {
        "part" : 68505342,
        "total" : 2812799660
      },
      "totalNumberOfFiles" : 6,
      "totalNumberOfFilesIndexedByExtensions" : 0,
      "totalFilesSize" : 158829,
      "indexValueChangerEvaluationSpeed" : {
        "totalBytes" : 158829,
        "totalCpuTime" : 68505342
      }
    }, {
      "indexId" : "fileIncludes",
      "shardsCount" : 1,
      "partOfTotalIndexingTime" : {
        "part" : 53421845,
        "total" : 2812799660
      },
      "totalNumberOfFiles" : 4,
      "totalNumberOfFilesIndexedByExtensions" : 0,
      "totalFilesSize" : 4975532,
      "indexValueChangerEvaluationSpeed" : {
        "totalBytes" : 4975532,
        "totalCpuTime" : 53421845
      }
    }, {
      "indexId" : "json.file.root.values",
      "shardsCount" : 1,
      "partOfTotalIndexingTime" : {
        "part" : 19111262,
        "total" : 2812799660
      },
      "totalNumberOfFiles" : 18,
      "totalNumberOfFilesIndexedByExtensions" : 0,
      "totalFilesSize" : 141190,
      "indexValueChangerEvaluationSpeed" : {
        "totalBytes" : 141190,
        "totalCpuTime" : 19111262
      }
    }, {
      "indexId" : "RelaxSymbolIndex",
      "shardsCount" : 1,
      "partOfTotalIndexingTime" : {
        "part" : 11603870,
        "total" : 2812799660
      },
      "totalNumberOfFiles" : 4,
      "totalNumberOfFilesIndexedByExtensions" : 0,
      "totalFilesSize" : 4975532,
      "indexValueChangerEvaluationSpeed" : {
        "totalBytes" : 4975532,
        "totalCpuTime" : 11603870
      }
    }, {
      "indexId" : "xmlProperties",
      "shardsCount" : 1,
      "partOfTotalIndexingTime" : {
        "part" : 11444310,
        "total" : 2812799660
      },
      "totalNumberOfFiles" : 4,
      "totalNumberOfFilesIndexedByExtensions" : 0,
      "totalFilesSize" : 4975532,
      "indexValueChangerEvaluationSpeed" : {
        "totalBytes" : 4975532,
        "totalCpuTime" : 11444310
      }
    }, {
      "indexId" : "org.jetbrains.kotlin.idea.vfilefinder.KotlinStdlibIndex",
      "shardsCount" : 1,
      "partOfTotalIndexingTime" : {
        "part" : 3854499,
        "total" : 2812799660
      },
      "totalNumberOfFiles" : 10,
      "totalNumberOfFilesIndexedByExtensions" : 0,
      "totalFilesSize" : 886305,
      "indexValueChangerEvaluationSpeed" : {
        "totalBytes" : 886305,
        "totalCpuTime" : 3854499
      }
    }, {
      "indexId" : "PluginIdModuleIndex",
      "shardsCount" : 1,
      "partOfTotalIndexingTime" : {
        "part" : 276087,
        "total" : 2812799660
      },
      "totalNumberOfFiles" : 4,
      "totalNumberOfFilesIndexedByExtensions" : 0,
      "totalFilesSize" : 4975532,
      "indexValueChangerEvaluationSpeed" : {
        "totalBytes" : 4975532,
        "totalCpuTime" : 276087
      }
    }, {
      "indexId" : "devkit.ExtensionPointClassIndex",
      "shardsCount" : 1,
      "partOfTotalIndexingTime" : {
        "part" : 69911,
        "total" : 2812799660
      },
      "totalNumberOfFiles" : 4,
      "totalNumberOfFilesIndexedByExtensions" : 0,
      "totalFilesSize" : 4975532,
      "indexValueChangerEvaluationSpeed" : {
        "totalBytes" : 4975532,
        "totalCpuTime" : 69911
      }
    }, {
      "indexId" : "PluginIdDependenciesIndex",
      "shardsCount" : 1,
      "partOfTotalIndexingTime" : {
        "part" : 40215,
        "total" : 2812799660
      },
      "totalNumberOfFiles" : 4,
      "totalNumberOfFilesIndexedByExtensions" : 0,
      "totalFilesSize" : 4975532,
      "indexValueChangerEvaluationSpeed" : {
        "totalBytes" : 4975532,
        "totalCpuTime" : 40215
      }
    }, {
      "indexId" : "IdeaPluginRegistrationIndex",
      "shardsCount" : 1,
      "partOfTotalIndexingTime" : {
        "part" : 37530,
        "total" : 2812799660
      },
      "totalNumberOfFiles" : 4,
      "totalNumberOfFilesIndexedByExtensions" : 0,
      "totalFilesSize" : 4975532,
      "indexValueChangerEvaluationSpeed" : {
        "totalBytes" : 4975532,
        "totalCpuTime" : 37530
      }
    }, {
      "indexId" : "devkit.ExtensionPointIndex",
      "shardsCount" : 1,
      "partOfTotalIndexingTime" : {
        "part" : 36570,
        "total" : 2812799660
      },
      "totalNumberOfFiles" : 4,
      "totalNumberOfFilesIndexedByExtensions" : 0,
      "totalFilesSize" : 4975532,
      "indexValueChangerEvaluationSpeed" : {
        "totalBytes" : 4975532,
        "totalCpuTime" : 36570
      }
    } ],
    "statisticsOfChangedDuringIndexingFiles" : {
      "numberOfFiles" : 33,
      "retrievingTime" : 3142539
    },
    "fileProviderStatistics" : [ {
      "providerName" : "Refreshed files",
      "totalNumberOfIndexedFiles" : 33,
      "totalNumberOfFilesFullyIndexedByExtensions" : 0,
      "totalNumberOfNothingToWriteFiles" : 0,
      "totalIndexingVisibleTime" : 886729355,
      "contentLoadingVisibleTime" : 39490076,
      "numberOfTooLargeForIndexingFiles" : 0,
      "slowIndexedFiles" : [ {
        "fileName" : "main.profile.xml",
        "processingTime" : 798059649,
        "evaluationOfIndexValueChangerTime" : 765563940,
        "contentLoadingTime" : 24944614
      }, {
        "fileName" : "promo.profile.xml",
        "processingTime" : 872859751,
        "evaluationOfIndexValueChangerTime" : 812325433,
        "contentLoadingTime" : 48482330
      } ],
      "filesFullyIndexedByExtensions" : [ ],
      "separateApplyingIndexesVisibleTime" : 35109702
    }, {
      "providerName" : "<indexing queue>",
      "totalNumberOfIndexedFiles" : 10,
      "totalNumberOfFilesFullyIndexedByExtensions" : 0,
      "totalNumberOfNothingToWriteFiles" : 0,
      "totalIndexingVisibleTime" : 322245860,
      "contentLoadingVisibleTime" : 38577644,
      "numberOfTooLargeForIndexingFiles" : 0,
      "slowIndexedFiles" : [ ],
      "filesFullyIndexedByExtensions" : [ ],
      "separateApplyingIndexesVisibleTime" : 77760373
    } ],
    "visibleTimeToAllThreadTimeRatio" : 0.3241821534886744
  }
}